igem_lite/__init__.py
igem_lite/epc/__init__.py
igem_lite/epc/clarite/__init__.py
igem_lite/epc/clarite/analyze/__init__.py
igem_lite/epc/clarite/analyze/analyze.py
igem_lite/epc/clarite/analyze/interaction.py
igem_lite/epc/clarite/describe/__init__.py
igem_lite/epc/clarite/describe/describe.py
igem_lite/epc/clarite/load/__init__.py
igem_lite/epc/clarite/load/load.py
igem_lite/epc/clarite/modify/__init__.py
igem_lite/epc/clarite/modify/modify.py
igem_lite/epc/clarite/plot/__init__.py
igem_lite/epc/clarite/plot/plot.py
igem_lite/epc/clarite/survey/__init__.py
igem_lite/epc/clarite/survey/survey.py
igem_lite/epc/tests/__init__.py
igem_lite/epc/tests/py_test_output/.gitignore
igem_lite/epc/tests/py_test_output/top_results_nhanesreal.png
igem_lite/epc/tests/py_test_output/top_results_nhanesreal_no_cutoff.png
igem_lite/epc/tests/py_test_output/top_results_nhanessmall.png
igem_lite/epc/tests/test_analyze/__init__.py
igem_lite/epc/tests/test_analyze/conftest.py
igem_lite/epc/tests/test_analyze/test_association_study.py
igem_lite/epc/tests/test_analyze/test_exe_pairwise.py
igem_lite/epc/tests/test_analyze/test_gwas.py
igem_lite/epc/tests/test_analyze/test_interaction_study.py
igem_lite/epc/tests/test_describe/__init__.py
igem_lite/epc/tests/test_describe/conftest.py
igem_lite/epc/tests/test_describe/test_describe.py
igem_lite/epc/tests/test_load/__init__.py
igem_lite/epc/tests/test_load/test_load.py
igem_lite/epc/tests/test_modify/__init__.py
igem_lite/epc/tests/test_modify/conftest.py
igem_lite/epc/tests/test_modify/test_modify.py
igem_lite/epc/tests/test_plot/__init__.py
igem_lite/epc/tests/test_plot/conftest.py
igem_lite/epc/tests/test_plot/test_plot.py
igem_lite/ge/__init__.py
igem_lite/ge/admin.py
igem_lite/ge/apps.py
igem_lite/ge/db/__init__.py
igem_lite/ge/db/get.py
igem_lite/ge/db/sync.py
igem_lite/ge/filter/__init__.py
igem_lite/ge/filter/convert.py
igem_lite/ge/filter/filters.py
igem_lite/ge/filter/genes.py
igem_lite/ge/filter/positions.py
igem_lite-0.1.7.dist-info/WHEEL
igem_lite-0.1.7.dist-info/METADATA
igem_lite-0.1.7.dist-info/RECORD
