Metadata-Version: 2.1
Name: igem-lite
Version: 0.1.7
Summary: 
License: BSD-3-Clause
Author: Andre Rico
Author-email: 97684721+AndreRicoPSU@users.noreply.github.com
Requires-Python: >=3.9.0,<3.11.0
Classifier: License :: OSI Approved :: BSD License
Classifier: Programming Language :: Python :: 3
Classifier: Programming Language :: Python :: 3.9
Classifier: Programming Language :: Python :: 3.10
Requires-Dist: clarite (==2.3.6)
Requires-Dist: dask (>=2023.7.1,<2024.0.0)
Requires-Dist: django (>=4.1.5,<5.0.0)
Requires-Dist: django-thread (>=0.0.1,<0.0.2)
Requires-Dist: pyensembl (>=2.3.9,<3.0.0)
Requires-Dist: requests (>=2.28.2,<3.0.0)
Requires-Dist: tqdm (>=4.66.1,<5.0.0)
Requires-Dist: xarray (>=2023.10.1,<2024.0.0)
